movens/__init__.py
movens/about.py
movens/cli.py
movens/main.py
movens-1.0.8.dist-info/LICENSE
movens-1.0.8.dist-info/METADATA
movens-1.0.8.dist-info/WHEEL
movens-1.0.8.dist-info/entry_points.txt
movens-1.0.8.dist-info/top_level.txt
movens-1.0.8.dist-info/RECORD
