Metadata-Version: 2.1
Name: movens
Version: 1.0.8
Summary: CLI tool to arrange files smartly
Home-page: https://github.com/codeperfectplus/movens
Author: codeperfectplus
Author-email: deepak008@live.com
Keywords: movens,file organizer,file manager,file sorting,file arrangement,file categorization,file classification,file organization tool,command line tool,CLI tool
Classifier: Development Status :: 5 - Production/Stable
Classifier: Programming Language :: Python :: 3
Classifier: License :: OSI Approved :: MIT License
Classifier: Operating System :: OS Independent
Classifier: Intended Audience :: End Users/Desktop
Requires-Python: >=3.1
License-File: LICENSE
